Led Panel/delay_unit.v
module delay_unit (
    input  wire clk,
    input  wire rst,
    input  wire [5:0] col,

    output wire clk_out,
    output reg latch,
    output reg oe
);
    // Desfase de reloj
    assign clk_out = ~clk;

    always @(posedge clk) begin
        if (rst) begin
            latch <= 0;
            oe    <= 1; 
        end else begin
            latch <= 0;
            oe    <= 0;

            // Latch al inicio de línea
            if (col == 0) begin
                latch <= 1; 
                oe    <= 1;
            end
            else if (col == 63) begin
                oe <= 1;
            end
        end
    end
endmodule

Led Panel/panel_pwm.v
module panel_pwm( 
    input  wire [23:0] pix_top,
    input  wire [23:0] pix_bottom,
    
    // s8bpp [7:0], 5bpp [4:0]
    input  wire [4:0]  pwm_level, 
    
    output wire r0, g0, b0,
    output wire r1, g1, b1
);

    // 1. Extraer el BYTE COMPLETO (8 bits) de cada color
    //    Rojo (23..16), Verde (15..8), Azul (7..0)
    /*
    wire [7:0] val_tR = pix_top[23:16];
    wire [7:0] val_tG = pix_top[15:8];
    wire [7:0] val_tB = pix_top[7:0];

    wire [7:0] val_bR = pix_bottom[23:16];
    wire [7:0] val_bG = pix_bottom[15:8];
    wire [7:0] val_bB = pix_bottom[7:0];
    */
    wire [4:0] val_tR = pix_top[23:19];
    wire [4:0] val_tG = pix_top[15:11];
    wire [4:0] val_tB = pix_top[7:3];

    wire [4:0] val_bR = pix_bottom[23:19];
    wire [4:0] val_bG = pix_bottom[15:11];
    wire [4:0] val_bB = pix_bottom[7:3];
    // 2. Lógica de Comparación
    // Esto genera 256 niveles de intensidad.
    
    assign r0 = (val_tR > pwm_level);
    assign g0 = (val_tG > pwm_level);
    assign b0 = (val_tB > pwm_level);

    assign r1 = (val_bR > pwm_level);
    assign g1 = (val_bG > pwm_level);
    assign b1 = (val_bB > pwm_level);

endmodule

Led Panel/panel_memory.v
module panel_memory(
    input  wire        clk,
    input  wire [11:0] addr_top,
    input  wire [11:0] addr_bottom,
    output reg  [23:0] pix_top,
    output reg  [23:0] pix_bottom
);

    reg [23:0] MEM [0:4095];

    initial begin
        $readmemh("image(1).hex", MEM);
    end

    always @(posedge clk) begin
        pix_top    <= MEM[addr_top];
        pix_bottom <= MEM[addr_bottom];
    end

endmodule

Led Panel/scan_counter.v
module scan_counters(
    input  wire clk,
    input  wire rst,

    output reg [5:0] col,
    output reg [4:0] scan_row,
    output reg [4:0] addr_out,
    
    // 8bpp [7:0], 5bpp [4:0]
    output reg [4:0] pwm_level, 
    
    output wire [5:0] row_top,
    output wire [5:0] row_bottom
);

    always @(posedge clk) begin
        if (rst) begin
            col <= 0;
            scan_row <= 0;
            addr_out <= 0;
            pwm_level <= 0;
        end else begin
            // 1. Columnas
            col <= col + 1;
            if (col == 63) begin
                col <= 0;
            end

            // 2. Sincronización de Fila
            if (col == 0) begin
                addr_out <= scan_row; 
            end

            // 3. Filas y Niveles de Brillo
            if (col == 1) begin
                scan_row <= scan_row + 1;
                
                if (scan_row == 31) begin
                    scan_row <= 0;
                    pwm_level <= pwm_level + 1; 
                end
            end
        end
    end

    assign row_top    = {1'b0, scan_row}; 
    assign row_bottom = {1'b1, scan_row}; 

endmodule

Led Panel/top.v
module top(
    input  wire clk,
    input  wire rst,

    output wire r0, g0, b0,
    output wire r1, g1, b1,
    output wire [4:0] addr,
    output wire clk_out,
    output wire latch,
    output wire oe
);

    wire [5:0] col;
    wire [4:0] scan_row;
    wire [4:0] display_row;
    wire [5:0] row_top;
    wire [5:0] row_bottom;
    
    // 8bpp [7:0], 5bpp [4:0]
    wire [4:0] pwm_level; 

    scan_counters SC(
        .clk(clk),
        .rst(rst),
        .col(col),
        .scan_row(scan_row),
        .addr_out(display_row),
        .pwm_level(pwm_level),
        .row_top(row_top),
        .row_bottom(row_bottom)
    );

    assign addr = display_row;

    wire [11:0] addr_top    = {row_top,    col};
    wire [11:0] addr_bottom = {row_bottom, col};
    wire [23:0] pix_top;
    wire [23:0] pix_bottom;

    panel_memory MEM(
        .clk(clk),
        .addr_top(addr_top),
        .addr_bottom(addr_bottom),
        .pix_top(pix_top),
        .pix_bottom(pix_bottom)
    );

    panel_pwm PWM(
        .pix_top(pix_top),
        .pix_bottom(pix_bottom),
        .pwm_level(pwm_level),
        .r0(r0), .g0(g0), .b0(b0),
        .r1(r1), .g1(g1), .b1(b1)
    );

    delay_unit DU(
        .clk(clk),
        .rst(rst),
        .col(col),
        .clk_out(clk_out),
        .latch(latch),
        .oe(oe)
    );

endmodule

Led Panel/tb.v
`timescale 1ns / 1ps

module tb;

    reg clk;
    reg rst;

    wire r0, g0, b0;
    wire r1, g1, b1;
    wire [4:0] addr;
    wire clk_out;
    wire latch;
    wire oe;

    // 2. Instanciar el Módulo TOP
    top UUT (
        .clk(clk),
        .rst(rst),
        .r0(r0), .g0(g0), .b0(b0),
        .r1(r1), .g1(g1), .b1(b1),
        .addr(addr),
        .clk_out(clk_out),
        .latch(latch),
        .oe(oe)
    );

    // 3. Generador de Reloj (25 MHz)
    // Periodo = 40ns (20ns alto, 20ns bajo)
    initial begin
        clk = 0;
        forever #20 clk = ~clk; 
    end

    // 4. Secuencia de Prueba
    initial begin
        // Configurar archivo de salida para GTKWave
        $dumpfile("build/hub75_simulation.vcd");
        $dumpvars(0, tb);

        // Inicio: Reset activo
        rst = 1;
        #100; // Esperar 100ns
        
        // Soltar Reset
        rst = 0;
        
        #50000; 

        $display("Simulación terminada.");
        $finish;
    end

endmodule

Led Panel/build/hub75_simulation.vcd
$date
	Tue Dec  9 01:27:17 2025
$end
$version
	Icarus Verilog
$end
$timescale
	1ps
$end
$scope module tb $end
$var wire 1 ! r1 $end
$var wire 1 " r0 $end
$var wire 1 # oe $end
$var wire 1 $ latch $end
$var wire 1 % g1 $end
$var wire 1 & g0 $end
$var wire 1 ' clk_out $end
$var wire 1 ( b1 $end
$var wire 1 ) b0 $end
$var wire 5 * addr [4:0] $end
$var reg 1 + clk $end
$var reg 1 , rst $end
$scope module UUT $end
$var wire 5 - addr [4:0] $end
$var wire 1 + clk $end
$var wire 1 , rst $end
$var wire 5 . scan_row [4:0] $end
$var wire 6 / row_top [5:0] $end
$var wire 6 0 row_bottom [5:0] $end
$var wire 1 ! r1 $end
$var wire 1 " r0 $end
$var wire 5 1 pwm_level [4:0] $end
$var wire 24 2 pix_top [23:0] $end
$var wire 24 3 pix_bottom [23:0] $end
$var wire 1 # oe $end
$var wire 1 $ latch $end
$var wire 1 % g1 $end
$var wire 1 & g0 $end
$var wire 5 4 display_row [4:0] $end
$var wire 6 5 col [5:0] $end
$var wire 1 ' clk_out $end
$var wire 1 ( b1 $end
$var wire 1 ) b0 $end
$var wire 12 6 addr_top [11:0] $end
$var wire 12 7 addr_bottom [11:0] $end
$scope module DU $end
$var wire 1 + clk $end
$var wire 1 ' clk_out $end
$var wire 1 , rst $end
$var wire 6 8 col [5:0] $end
$var reg 1 $ latch $end
$var reg 1 # oe $end
$upscope $end
$scope module MEM $end
$var wire 12 9 addr_bottom [11:0] $end
$var wire 12 : addr_top [11:0] $end
$var wire 1 + clk $end
$var reg 24 ; pix_bottom [23:0] $end
$var reg 24 < pix_top [23:0] $end
$upscope $end
$scope module PWM $end
$var wire 24 = pix_bottom [23:0] $end
$var wire 24 > pix_top [23:0] $end
$var wire 5 ? val_tR [4:0] $end
$var wire 5 @ val_tG [4:0] $end
$var wire 5 A val_tB [4:0] $end
$var wire 5 B val_bR [4:0] $end
$var wire 5 C val_bG [4:0] $end
$var wire 5 D val_bB [4:0] $end
$var wire 1 ! r1 $end
$var wire 1 " r0 $end
$var wire 5 E pwm_level [4:0] $end
$var wire 1 % g1 $end
$var wire 1 & g0 $end
$var wire 1 ( b1 $end
$var wire 1 ) b0 $end
$upscope $end
$scope module SC $end
$var wire 1 + clk $end
$var wire 1 , rst $end
$var wire 6 F row_top [5:0] $end
$var wire 6 G row_bottom [5:0] $end
$var reg 5 H addr_out [4:0] $end
$var reg 6 I col [5:0] $end
$var reg 5 J pwm_level [4:0] $end
$var reg 5 K scan_row [4:0] $end
$upscope $end
$upscope $end
$upscope $end
$enddefinitions $end
$comment Show the parameter values. $end
$dumpall
$end
#0
$dumpvars
bx K
bx J
bx I
bx H
b1xxxxx G
b0xxxxx F
bx E
bx D
bx C
bx B
bx A
bx @
bx ?
bx >
bx =
bx <
bx ;
b0xxxxxxxxxxx :
b1xxxxxxxxxxx 9
bx 8
b1xxxxxxxxxxx 7
b0xxxxxxxxxxx 6
bx 5
bx 4
bx 3
bx 2
bx 1
b1xxxxx 0
b0xxxxx /
bx .
bx -
1,
0+
bx *
x)
x(
1'
x&
x%
x$
x#
x"
x!
$end
#20000
b0 1
b0 E
b0 J
b0 *
b0 -
b0 4
b0 H
b0 /
b0 F
b100000 0
b100000 G
b0 .
b0 K
b100000000000 7
b100000000000 9
b0 6
b0 :
b0 5
b0 8
b0 I
1#
0$
0'
1+
#40000
1'
0+
#60000
1!
b1101 B
1%
b10010 C
1(
b10110 D
0"
b0 ?
0&
b0 @
1)
b11 A
b11011001001000010110000 3
b11011001001000010110000 ;
b11011001001000010110000 =
b1000000000100011111 2
b1000000000100011111 <
b1000000000100011111 >
0'
1+
#80000
1'
0+
#100000
b100000000001 7
b100000000001 9
b1 6
b1 :
b1 5
b1 8
b1 I
1$
1#
0'
1+
0,
#120000
1'
0+
#140000
b10011 B
b11001 C
b11011 D
1"
b10 ?
1&
b10 @
b101 A
0#
0$
b100111111100100011011100 3
b100111111100100011011100 ;
b100111111100100011011100 =
b101100001001000101000 2
b101100001001000101000 <
b101100001001000101000 >
b1 /
b1 F
b100001 0
b100001 G
b1 .
b1 K
b100001000010 7
b100001000010 9
b1000010 6
b1000010 :
b10 5
b10 8
b10 I
0'
1+
#160000
1'
0+
#180000
b1 B
b1011 C
b10001 D
0"
b0 ?
0&
b0 @
b100 A
b100001000011 7
b100001000011 9
b1000011 6
b1000011 :
b11 5
b11 8
b11 I
b10010101100110001111 3
b10010101100110001111 ;
b10010101100110001111 =
b100000000000100000 2
b100000000000100000 <
b100000000000100000 >
0'
1+
#200000
1'
0+
#220000
b1001 B
b1111 C
b10011 D
b10010010111111010011111 3
b10010010111111010011111 ;
b10010010111111010011111 =
b1010000000100100000 2
b1010000000100100000 <
b1010000000100100000 >
b100001000100 7
b100001000100 9
b1000100 6
b1000100 :
b100 5
b100 8
b100 I
0'
1+
#240000
1'
0+
#260000
b101 B
b111 C
b1010 D
b100001000101 7
b100001000101 9
b1000101 6
b1000101 :
b101 5
b101 8
b101 I
b1011110011111101010010 3
b1011110011111101010010 ;
b1011110011111101010010 =
b1100000010000100011 2
b1100000010000100011 <
b1100000010000100011 >
0'
1+
#280000
1'
0+
#300000
0!
b0 B
b101 C
b1011 D
b1010010101101011001 3
b1010010101101011001 ;
b1010010101101011001 =
b1100000001100100010 2
b1100000001100100010 <
b1100000001100100010 >
b100001000110 7
b100001000110 9
b1000110 6
b1000110 :
b110 5
b110 8
b110 I
0'
1+
#320000
1'
0+
#340000
1!
b1001 B
b10000 C
b10110 D
b100001000111 7
b100001000111 9
b1000111 6
b1000111 :
b111 5
b111 8
b111 I
b10011011000011010110000 3
b10011011000011010110000 ;
b10011011000011010110000 =
b1000000000100100000 2
b1000000000100100000 <
b1000000000100100000 >
0'
1+
#360000
1'
0+
#380000
b11 B
b111 C
b1100 D
b110110011101101100110 3
b110110011101101100110 ;
b110110011101101100110 =
b1010000001000100001 2
b1010000001000100001 <
b1010000001000100001 >
b100001001000 7
b100001001000 9
b1001000 6
b1001000 :
b1000 5
b1000 8
b1000 I
0'
1+
#400000
1'
0+
#420000
b110 C
b100001001001 7
b100001001001 9
b1001001 6
b1001001 :
b1001 5
b1001 8
b1001 I
b110010011010101100111 3
b110010011010101100111 ;
b110010011010101100111 =
b1110000010100100100 2
b1110000010100100100 <
b1110000010100100100 >
0'
1+
#440000
1'
0+
#460000
b110110011011101100110 3
b110110011011101100110 ;
b110110011011101100110 =
b1100000010000100011 2
b1100000010000100011 <
b1100000010000100011 >
b100001001010 7
b100001001010 9
b1001010 6
b1001010 :
b1010 5
b1010 8
b1010 I
0'
1+
#480000
1'
0+
#500000
b1000 B
b1101 C
b10011 D
b100001001011 7
b100001001011 9
b1001011 6
b1001011 :
b1011 5
b1011 8
b1011 I
b10001000110110010011011 3
b10001000110110010011011 ;
b10001000110110010011011 =
b1010000001000100000 2
b1010000001000100000 <
b1010000001000100000 >
0'
1+
#520000
1'
0+
#540000
b10000 B
b10101 C
b11011 D
b10 A
b100001011010111111011101 3
b100001011010111111011101 ;
b100001011010111111011101 =
b10100 2
b10100 <
b10100 >
b100001001100 7
b100001001100 9
b1001100 6
b1001100 :
b1100 5
b1100 8
b1100 I
0'
1+
#560000
1'
0+
#580000
b10110 C
1"
b1110 ?
1&
b1110 @
b1101 A
b100001001101 7
b100001001101 9
b1001101 6
b1001101 :
b1101 5
b1101 8
b1101 I
b100001001011000111011100 3
b100001001011000111011100 ;
b100001001011000111011100 =
b11101110111010001101101 2
b11101110111010001101101 <
b11101110111010001101101 >
0'
1+
#600000
1'
0+
#620000
b1101 B
b10100 C
b111 ?
b111 @
b1000 A
b11011111010011011011000 3
b11011111010011011011000 ;
b11011111010011011011000 =
b1111010011100101000101 2
b1111010011100101000101 <
b1111010011100101000101 >
b100001001110 7
b100001001110 9
b1001110 6
b1001110 :
b1110 5
b1110 8
b1110 I
0'
1+
#640000
1'
0+
#660000
b100 B
b1001 C
b1111 D
0"
b0 ?
0&
b0 @
b10 A
b100001001111 7
b100001001111 9
b1001111 6
b1001111 :
b1111 5
b1111 8
b1111 I
b1000010100101101111101 3
b1000010100101101111101 ;
b1000010100101101111101 =
b10000000000010100 2
b10000000000010100 <
b10000000000010100 >
0'
1+
#680000
1'
0+
#700000
0!
b0 B
b11 C
b1001 D
1"
b110 ?
1&
b110 @
b1011 A
b1110001001011 3
b1110001001011 ;
b1110001001011 =
b1100100011000101011001 2
b1100100011000101011001 <
b1100100011000101011001 >
b100001010000 7
b100001010000 9
b1010000 6
b1010000 :
b10000 5
b10000 8
b10000 I
0'
1+
#720000
1'
0+
#740000
1!
b1 B
b110 C
b1100 D
0"
b0 ?
0&
b0 @
b11 A
b100001010001 7
b100001010001 9
b1010001 6
b1010001 :
b10001 5
b10001 8
b10001 I
b10100011011101100111 3
b10100011011101100111 ;
b10100011011101100111 =
b1100000011000011111 2
b1100000011000011111 <
b1100000011000011111 >
0'
1+
#760000
1'
0+
#780000
b111 B
b1011 C
b10010 D
1"
b1010 ?
1&
b1001 @
b1010 A
b1110100101101010010010 3
b1110100101101010010010 ;
b1110100101101010010010 =
b10100000100111001010000 2
b10100000100111001010000 <
b10100000100111001010000 >
b100001010010 7
b100001010010 9
b1010010 6
b1010010 :
b10010 5
b10010 8
b10010 I
0'
1+
#800000
1'
0+
#820000
b101 B
b1000 C
b1110 D
b1001 ?
b1000 @
b1001 A
b100001010011 7
b100001010011 9
b1010011 6
b1010011 :
b10011 5
b10011 8
b10011 I
b1010000100000001110100 3
b1010000100000001110100 ;
b1010000100000001110100 =
b10010110100011101001100 2
b10010110100011101001100 <
b10010110100011101001100 >
0'
1+
#840000
1'
0+
#860000
b1 B
b11 C
b1001 D
0"
b0 ?
0&
b0 @
b10 A
b10110001110101001001 3
b10110001110101001001 ;
b10110001110101001001 =
b100000000100010111 2
b100000000100010111 <
b100000000100010111 >
b100001010100 7
b100001010100 9
b1010100 6
b1010100 :
b10100 5
b10100 8
b10100 I
0'
1+
#880000
1'
0+
#900000
b10 B
b1010 C
b10000 D
b100 A
b100001010101 7
b100001010101 9
b1010101 6
b1010101 :
b10101 5
b10101 8
b10101 I
b101110101001110000111 3
b101110101001110000111 ;
b101110101001110000111 =
b1110000010000100011 2
b1110000010000100011 <
b1110000010000100011 >
0'
1+
#920000
1'
0+
#940000
b1000 C
b1101 D
b11 A
b100000100001101101001 3
b100000100001101101001 ;
b100000100001101101001 =
b10000000000011100 2
b10000000000011100 <
b10000000000011100 >
b100001010110 7
b100001010110 9
b1010110 6
b1010110 :
b10110 5
b10110 8
b10110 I
0'
1+
#960000
1'
0+
#980000
b11000 B
b10111 C
b10100 D
1"
b10 ?
1&
b10 @
b110 A
b100001010111 7
b100001010111 9
b1010111 6
b1010111 :
b10111 5
b10111 8
b10111 I
b110001001011111110100101 3
b110001001011111110100101 ;
b110001001011111110100101 =
b101110001010000110101 2
b101110001010000110101 <
b101110001010000110101 >
0'
1+
#1000000
1'
0+
#1020000
b11111 B
b11111 C
b11100 D
b110 ?
b110 @
b1011 A
b111111001111110111100101 3
b111111001111110111100101 ;
b111111001111110111100101 =
b1101000011010101011000 2
b1101000011010101011000 <
b1101000011010101011000 >
b100001011000 7
b100001011000 9
b1011000 6
b1011000 :
b11000 5
b11000 8
b11000 I
0'
1+
#1040000
1'
0+
#1060000
b11010 D
0"
b0 ?
0&
b0 @
b11 A
b100001011001 7
b100001011001 9
b1011001 6
b1011001 :
b11001 5
b11001 8
b11001 I
b111110101111101011010111 3
b111110101111101011010111 ;
b111110101111101011010111 =
b10000000000011001 2
b10000000000011001 <
b10000000000011001 >
0'
1+
#1080000
1'
0+
#1100000
b11011 D
b100 A
b111111011111110111011001 3
b111111011111110111011001 ;
b111111011111110111011001 =
b1100000010000100011 2
b1100000010000100011 <
b1100000010000100011 >
b100001011010 7
b100001011010 9
b1011010 6
b1011010 :
b11010 5
b11010 8
b11010 I
0'
1+
#1120000
1'
0+
#1140000
b100001011011 7
b100001011011 9
b1011011 6
b1011011 :
b11011 5
b11011 8
b11011 I
b111111011111110111011011 3
b111111011111110111011011 ;
b111111011111110111011011 =
b1010000001000100000 2
b1010000001000100000 <
b1010000001000100000 >
0'
1+
#1160000
1'
0+
#1180000
b111111001111110111011011 3
b111111001111110111011011 ;
b111111001111110111011011 =
b1100000001100100010 2
b1100000001100100010 <
b1100000001100100010 >
b100001011100 7
b100001011100 9
b1011100 6
b1011100 :
b11100 5
b11100 8
b11100 I
0'
1+
#1200000
1'
0+
#1220000
b100001011101 7
b100001011101 9
b1011101 6
b1011101 :
b11101 5
b11101 8
b11101 I
b1010000001000100001 2
b1010000001000100001 <
b1010000001000100001 >
0'
1+
#1240000
1'
0+
#1260000
b11 A
b111111001111111011011001 3
b111111001111111011011001 ;
b111111001111111011011001 =
b10000000000011110 2
b10000000000011110 <
b10000000000011110 >
b100001011110 7
b100001011110 9
b1011110 6
b1011110 :
b11110 5
b11110 8
b11110 I
0'
1+
#1280000
1'
0+
#1300000
b100001011111 7
b100001011111 9
b1011111 6
b1011111 :
b11111 5
b11111 8
b11111 I
b11110 2
b11110 <
b11110 >
0'
1+
#1320000
1'
0+
#1340000
b100 A
b10000001000100001 2
b10000001000100001 <
b10000001000100001 >
b100001100000 7
b100001100000 9
b1100000 6
b1100000 :
b100000 5
b100000 8
b100000 I
0'
1+
#1360000
1'
0+
#1380000
b10 A
b100001100001 7
b100001100001 9
b1100001 6
b1100001 :
b100001 5
b100001 8
b100001 I
b10011 2
b10011 <
b10011 >
0'
1+
#1400000
1'
0+
#1420000
1"
b1110 ?
1&
b1100 @
b1001 A
b11101110110000101001011 2
b11101110110000101001011 <
b11101110110000101001011 >
b100001100010 7
b100001100010 9
b1100010 6
b1100010 :
b100010 5
b100010 8
b100010 I
0'
1+
#1440000
1'
0+
#1460000
b11111 ?
b11111 @
b11001 A
b100001100011 7
b100001100011 9
b1100011 6
b1100011 :
b100011 5
b100011 8
b100011 I
b111111111111111111001110 2
b111111111111111111001110 <
b111111111111111111001110 >
0'
1+
#1480000
1'
0+
#1500000
b10011 ?
b1100 @
b1000 A
b100111110110001001000111 2
b100111110110001001000111 <
b100111110110001001000111 >
b100001100100 7
b100001100100 9
b1100100 6
b1100100 :
b100100 5
b100100 8
b100100 I
0'
1+
#1520000
1'
0+
#1540000
0"
b0 ?
0&
b0 @
b10 A
b100001100101 7
b100001100101 9
b1100101 6
b1100101 :
b100101 5
b100101 8
b100101 I
b111110111111101111011001 3
b111110111111101111011001 ;
b111110111111101111011001 =
b10111 2
b10111 <
b10111 >
0'
1+
#1560000
1'
0+
#1580000
b11 A
b111111011111110011011010 3
b111111011111110011011010 ;
b111111011111110011011010 =
b10000000100011111 2
b10000000100011111 <
b10000000100011111 >
b100001100110 7
b100001100110 9
b1100110 6
b1100110 :
b100110 5
b100110 8
b100110 I
0'
1+
#1600000
1'
0+
#1620000
b100001100111 7
b100001100111 9
b1100111 6
b1100111 :
b100111 5
b100111 8
b100111 I
b111111111111111111011101 3
b111111111111111111011101 ;
b111111111111111111011101 =
b11111 2
b11111 <
b11111 >
0'
1+
#1640000
1'
0+
#1660000
b10111 B
b11100 C
b11010 D
b100 A
b101111101110001111010111 3
b101111101110001111010111 ;
b101111101110001111010111 =
b10000000000100000 2
b10000000000100000 <
b10000000000100000 >
b100001101000 7
b100001101000 9
b1101000 6
b1101000 :
b101000 5
b101000 8
b101000 I
0'
1+
#1680000
1'
0+
#1700000
b101 B
b1001 C
b1110 D
b11 A
b100001101001 7
b100001101001 9
b1101001 6
b1101001 :
b101001 5
b101001 8
b101001 I
b1010000100111001110001 3
b1010000100111001110001 ;
b1010000100111001110001 =
b1000000000000011110 2
b1000000000000011110 <
b1000000000000011110 >
0'
1+
#1720000
1'
0+
#1740000
b11011 B
b1010 D
b110111110100101001010010 3
b110111110100101001010010 ;
b110111110100101001010010 =
b10000000000011101 2
b10000000000011101 <
b10000000000011101 >
b100001101010 7
b100001101010 9
b1101010 6
b1101010 :
b101010 5
b101010 8
b101010 I
0'
1+
#1760000
1'
0+
#1780000
b11110 B
b1000 C
b100 A
b100001101011 7
b100001101011 9
b1101011 6
b1101011 :
b101011 5
b101011 8
b101011 I
b111100000100001101010100 3
b111100000100001101010100 ;
b111100000100001101010100 =
b1110000010000100100 2
b1110000010000100100 <
b1110000010000100100 >
0'
1+
#1800000
1'
0+
#1820000
b1001 B
b111 C
b1100 D
b10 A
b10010110011100101100001 3
b10010110011100101100001 ;
b10010110011100101100001 =
b10010 2
b10010 <
b10010 >
b100001101100 7
b100001101100 9
b1101100 6
b1101100 :
b101100 5
b101100 8
b101100 I
0'
1+
#1840000
1'
0+
#1860000
0!
b0 B
b1111 C
b10101 D
1"
b1000 ?
1&
b1001 @
b1101 A
b100001101101 7
b100001101101 9
b1101101 6
b1101101 :
b101101 5
b101101 8
b101101 I
b111101110101011 3
b111101110101011 ;
b111101110101011 =
b10000100100111001101110 2
b10000100100111001101110 <
b10000100100111001101110 >
0'
1+
#1880000
1'
0+
#1900000
b10000 C
b10110 D
b10 ?
b10 @
b110 A
b1001000000110110000 3
b1001000000110110000 ;
b1001000000110110000 =
b100000001000000110011 2
b100000001000000110011 <
b100000001000000110011 >
b100001101110 7
b100001101110 9
b1101110 6
b1101110 :
b101110 5
b101110 8
b101110 I
0'
1+
#1920000
1'
0+
#1940000
0"
b0 ?
0&
b0 @
b11 A
b100001101111 7
b100001101111 9
b1101111 6
b1101111 :
b101111 5
b101111 8
b101111 I
b11000011010110011 3
b11000011010110011 ;
b11000011010110011 =
b11000 2
b11000 <
b11000 >
0'
1+
#1960000
1'
0+
#1980000
b1101 C
b10100 D
b100 A
b1010110100010100001 3
b1010110100010100001 ;
b1010110100010100001 =
b1110000010000100001 2
b1110000010000100001 <
b1110000010000100001 >
b100001110000 7
b100001110000 9
b1110000 6
b1110000 :
b110000 5
b110000 8
b110000 I
0'
1+
#2000000
1'
0+
#2020000
1!
b1 B
b111 C
b101 D
b11 A
b100001110001 7
b100001110001 9
b1110001 6
b1110001 :
b110001 5
b110001 8
b110001 I
b10100011101000101010 3
b10100011101000101010 ;
b10100011101000101010 =
b100000000100011011 2
b100000000100011011 <
b100000000100011011 >
0'
1+
#2040000
1'
0+
#2060000
0!
b0 B
b1000 C
b11 D
1"
b101 ?
1&
b100 @
b110 A
b1010100000000011010 3
b1010100000000011010 ;
b1010100000000011010 =
b1010010010011000110100 2
b1010010010011000110100 <
b1010010010011000110100 >
b100001110010 7
b100001110010 9
b1110010 6
b1110010 :
b110010 5
b110010 8
b110010 I
0'
1+
#2080000
1'
0+
#2100000
1!
b1 B
b10 C
b110 ?
b110 @
b111 A
b100001110011 7
b100001110011 9
b1110011 6
b1110011 :
b110011 5
b110011 8
b110011 I
b11000001000100011110 3
b11000001000100011110 ;
b11000001000100011110 =
b1101000011000100111100 2
b1101000011000100111100 <
b1101000011000100111100 >
0'
1+
#2120000
1'
0+
#2140000
b100 B
b1000 C
b1101 D
0"
b0 ?
0&
b0 @
b11 A
b1000110100000001101011 3
b1000110100000001101011 ;
b1000110100000001101011 =
b100000000100011010 2
b100000000100011010 <
b100000000100011010 >
b100001110100 7
b100001110100 9
b1110100 6
b1110100 :
b110100 5
b110100 8
b110100 I
0'
1+
#2160000
1'
0+
#2180000
b1010 B
b1110 C
b10100 D
b100 A
b100001110101 7
b100001110101 9
b1110101 6
b1110101 :
b110101 5
b110101 8
b110101 I
b10100100111011010100010 3
b10100100111011010100010 ;
b10100100111011010100010 =
b1110000010000100010 2
b1110000010000100010 <
b1110000010000100010 >
0'
1+
#2200000
1'
0+
#2220000
b1 B
b111 C
b1101 D
b11 A
b11110011101101101011 3
b11110011101101101011 ;
b11110011101101101011 =
b110000000100011111 2
b110000000100011111 <
b110000000100011111 >
b100001110110 7
b100001110110 9
b1110110 6
b1110110 :
b110110 5
b110110 8
b110110 I
0'
1+
#2240000
1'
0+
#2260000
0!
b0 B
b100 C
b1010 D
1"
b10 ?
1&
b10 @
b101 A
b100001110111 7
b100001110111 9
b1110111 6
b1110111 :
b110111 5
b110111 8
b110111 I
b10001101010001 3
b10001101010001 ;
b10001101010001 =
b101100001001100101010 2
b101100001001100101010 <
b101100001001100101010 >
0'
1+
#2280000
1'
0+
#2300000
1!
b1000 B
b1111 C
b10101 D
b1000 ?
b111 @
b1000 A
b10000010111100010101101 3
b10000010111100010101101 ;
b10000010111100010101101 =
b10000010011111001000011 2
b10000010011111001000011 <
b10000010011111001000011 >
b100001111000 7
b100001111000 9
b1111000 6
b1111000 :
b111000 5
b111000 8
b111000 I
0'
1+
#2320000
1'
0+
#2340000
b1111 B
b10101 C
b11011 D
0"
b0 ?
0&
b0 @
b11 A
b100001111001 7
b100001111001 9
b1111001 6
b1111001 :
b111001 5
b111001 8
b111001 I
b11110101010101011011001 3
b11110101010101011011001 ;
b11110101010101011011001 =
b100000000100011011 2
b100000000100011011 <
b100000000100011011 >
0'
1+
#2360000
1'
0+
#2380000
b10000 B
b10110 C
b100001111011010011011110 3
b100001111011010011011110 ;
b100001111011010011011110 =
b100000000000011110 2
b100000000000011110 <
b100000000000011110 >
b100001111010 7
b100001111010 9
b1111010 6
b1111010 :
b111010 5
b111010 8
b111010 I
0'
1+
#2400000
1'
0+
#2420000
b1110 B
b10100 C
b11001 D
b100001111011 7
b100001111011 9
b1111011 6
b1111011 :
b111011 5
b111011 8
b111011 I
b11100101010001011001111 3
b11100101010001011001111 ;
b11100101010001011001111 =
b1000000001000011111 2
b1000000001000011111 <
b1000000001000011111 >
0'
1+
#2440000
1'
0+
#2460000
b100 B
b1001 C
b1111 D
1"
b1 ?
1&
b1 @
b101 A
b1001110100101001111100 3
b1001110100101001111100 ;
b1001110100101001111100 =
b10000000101100101001 2
b10000000101100101001 <
b10000000101100101001 >
b100001111100 7
b100001111100 9
b1111100 6
b1111100 :
b111100 5
b111100 8
b111100 I
0'
1+
#2480000
1'
0+
#2500000
b111 C
b1101 D
b10 @
b110 A
b100001111101 7
b100001111101 9
b1111101 6
b1111101 :
b111101 5
b111101 8
b111101 I
b1000000011110001101010 3
b1000000011110001101010 ;
b1000000011110001101010 =
b10110001000000110000 2
b10110001000000110000 <
b10110001000000110000 >
0'
1+
#2520000
1'
0+
#2540000
b11 B
b1000 C
0"
b0 ?
0&
b0 @
b100 A
b111000100001001101101 3
b111000100001001101101 ;
b111000100001001101101 =
b1100000010000100001 2
b1100000010000100001 <
b1100000010000100001 >
b100001111110 7
b100001111110 9
b1111110 6
b1111110 :
b111110 5
b111110 8
b111110 I
0'
1+
#2560000
1'
0+
#2580000
b1 B
b110 C
b1100 D
b100001111111 7
b100001111111 9
b1111111 6
b1111111 :
b111111 5
b111111 8
b111111 I
b10100011011001100011 3
b10100011011001100011 ;
b10100011011001100011 =
b1010000001100100001 2
b1010000001100100001 <
b1010000001100100001 >
0'
1+
#2600000
1'
0+
#2620000
b11 A
1#
b11010011011101100011 3
b11010011011101100011 ;
b11010011011101100011 =
b1010000000100011111 2
b1010000000100011111 <
b1010000000100011111 >
b100001000000 7
b100001000000 9
b1000000 6
b1000000 :
b0 5
b0 8
b0 I
0'
1+
#2640000
1'
0+
#2660000
0!
b0 B
b1010 C
b10001 D
b100 A
b1 *
b1 -
b1 4
b1 H
b100001000001 7
b100001000001 9
b1000001 6
b1000001 :
b1 5
b1 8
b1 I
b1010101001010001100 3
b1010101001010001100 ;
b1010101001010001100 =
b1010000001000100010 2
b1010000001000100010 <
b1010000001000100010 >
1$
1#
0'
1+
#2680000
1'
0+
#2700000
b110 C
b1100 D
b11 A
0#
0$
b11010101100101 3
b11010101100101 ;
b11010101100101 =
b100000000000011111 2
b100000000000011111 <
b100000000000011111 >
b10 /
b10 F
b100010 0
b100010 G
b10 .
b10 K
b100010000010 7
b100010000010 9
b10000010 6
b10000010 :
b10 5
b10 8
b10 I
0'
1+
#2720000
1'
0+
#2740000
1!
b11000 B
b11101 C
b11110 D
b100 A
b100010000011 7
b100010000011 9
b10000011 6
b10000011 :
b11 5
b11 8
b11 I
b110001101110110011110110 3
b110001101110110011110110 ;
b110001101110110011110110 =
b1010000001100100001 2
b1010000001100100001 <
b1010000001100100001 >
0'
1+
#2760000
1'
0+
